expecting/__init__.py
expecting/core.py
expecting/dict/__init__.py
expecting/enum/__init__.py
expecting/list/__init__.py
expecting/number/__init__.py
expecting/string/__init__.py
expecting/string/datetime.py
expecting/string/url.py
expecting/string/uuid.py
expecting-0.0.8.dist-info/METADATA
expecting-0.0.8.dist-info/WHEEL
expecting-0.0.8.dist-info/licenses/LICENSE
expecting-0.0.8.dist-info/RECORD
